odoo8_addon_runbot_language-8.0.1.1.0-py2.7-nspkg.pth
odoo_addons/runbot_language/__openerp__.py
odoo_addons/runbot_language/__init__.py
odoo_addons/runbot_language/README.rst
odoo_addons/runbot_language/models/runbot_build.py
odoo_addons/runbot_language/models/__init__.py
odoo_addons/runbot_language/models/runbot_repo.py
odoo_addons/runbot_language/views/runbot_build_views.xml
odoo_addons/runbot_language/views/runbot_repo_views.xml
odoo8_addon_runbot_language-8.0.1.1.0.dist-info/top_level.txt
odoo8_addon_runbot_language-8.0.1.1.0.dist-info/WHEEL
odoo8_addon_runbot_language-8.0.1.1.0.dist-info/RECORD
odoo8_addon_runbot_language-8.0.1.1.0.dist-info/metadata.json
odoo8_addon_runbot_language-8.0.1.1.0.dist-info/DESCRIPTION.rst
odoo8_addon_runbot_language-8.0.1.1.0.dist-info/METADATA
odoo8_addon_runbot_language-8.0.1.1.0.dist-info/namespace_packages.txt
